weaver/__init__.py
weaver/cli.py
weaver/config.py
weaver/generators/__init__.py
weaver/generators/base.py
weaver/generators/cookiecutter.py
weaver/templates/__init__.py
weaver/templates/entity-resolution/CLAUDE.md
weaver/templates/entity-resolution/README.md
weaver/templates/entity-resolution/cookiecutter.json
weaver/templates/entity-resolution/hooks/post_gen_project.py
weaver/templates/entity-resolution/hooks/pre_gen_project.py
weaver/templates/entity-resolution/{{cookiecutter.project_slug}}/.env.example
weaver/templates/entity-resolution/{{cookiecutter.project_slug}}/.gitignore
weaver/templates/entity-resolution/{{cookiecutter.project_slug}}/README.md
weaver/templates/entity-resolution/{{cookiecutter.project_slug}}/docker-compose.yml
weaver/templates/entity-resolution/{{cookiecutter.project_slug}}/pyproject.toml
weaver/templates/entity-resolution/{{cookiecutter.project_slug}}/src/__init__.py
weaver/templates/entity-resolution/{{cookiecutter.project_slug}}/src/api_django/__init__.py
weaver/templates/entity-resolution/{{cookiecutter.project_slug}}/src/api_django/views.py
weaver/templates/entity-resolution/{{cookiecutter.project_slug}}/src/api_fastapi/__init__.py
weaver/templates/entity-resolution/{{cookiecutter.project_slug}}/src/api_fastapi/routes.py
weaver/templates/entity-resolution/{{cookiecutter.project_slug}}/src/api_flask/__init__.py
weaver/templates/entity-resolution/{{cookiecutter.project_slug}}/src/api_flask/routes.py
weaver/templates/entity-resolution/{{cookiecutter.project_slug}}/src/config/__init__.py
weaver/templates/entity-resolution/{{cookiecutter.project_slug}}/src/config/settings.py
weaver/templates/entity-resolution/{{cookiecutter.project_slug}}/src/extractors/__init__.py
weaver/templates/entity-resolution/{{cookiecutter.project_slug}}/src/extractors/base_extractor.py
weaver/templates/entity-resolution/{{cookiecutter.project_slug}}/src/extractors/playwright.py
data_weaver_cli-0.1.9.dist-info/METADATA
data_weaver_cli-0.1.9.dist-info/WHEEL
data_weaver_cli-0.1.9.dist-info/entry_points.txt
data_weaver_cli-0.1.9.dist-info/top_level.txt
data_weaver_cli-0.1.9.dist-info/RECORD
