Metadata-Version: 2.4
Name: data-weaver-cli
Version: 0.1.9
Summary: 🕷️ Weave your data into beautiful connections
Author-email: Adrian Moses <adrian@adrianmoses.com>
License: MIT
Project-URL: Homepage, https://github.com/adrianmoses/weaver
Project-URL: Repository, https://github.com/adrianmoses/weaver
Project-URL: Issues, https://github.com/adrianmoses/weaver/issues
Keywords: scaffolding,project-template,cookiecutter,cli
Classifier: Development Status :: 3 - Alpha
Classifier: Intended Audience :: Developers
Classifier: License :: OSI Approved :: MIT License
Classifier: Programming Language :: Python :: 3
Classifier: Programming Language :: Python :: 3.12
Classifier: Topic :: Software Development :: Code Generators
Requires-Python: >=3.12
Requires-Dist: cookiecutter>=2.6.0
Requires-Dist: rich>=14.1.0
Requires-Dist: typer>=0.17.3
